AUTHORS.rst
CONTRIBUTING.rst
HISTORY.rst
LICENSE
MANIFEST.in
README.rst
setup.cfg
setup.py
docs/Makefile
docs/authors.rst
docs/conf.py
docs/contributing.rst
docs/history.rst
docs/index.rst
docs/installation.rst
docs/make.bat
docs/readme.rst
docs/usage.rst
nginx/__init__.py
nginx/config
nginx/cycle.pyx
nginx/hooks.py
nginx/log.pyx
nginx/module.py
nginx/nginx.pyx
nginx/nginx_config.pxd
nginx/nginx_core.pxd
nginx/nginx_event.pxd
nginx/ngx_python_module.c
nginx/ngx_python_module_modules.c
nginx/asyncio/__init__.py
nginx/asyncio/loop.pyx
nginx/asyncio/module.py
nginxpy.egg-info/PKG-INFO
nginxpy.egg-info/SOURCES.txt
nginxpy.egg-info/dependency_links.txt
nginxpy.egg-info/entry_points.txt
nginxpy.egg-info/not-zip-safe
nginxpy.egg-info/top_level.txt
tests/__init__.py
tests/test_nginxpy.py