Metadata-Version: 1.1
Name: nginxpy
Version: 0.1.0
Summary: Embed Python in NGINX.
Home-page: https://github.com/decentfox/nginxpy
Author: DecentFoX Studio
Author-email: foss@decentfox.com
License: Apache Software License 2.0
Keywords: nginxpy
Platform: UNKNOWN
Classifier: Development Status :: 2 - Pre-Alpha
Classifier: Intended Audience :: Developers
Classifier: License :: OSI Approved :: Apache Software License
Classifier: Natural Language :: English
Classifier: Programming Language :: Python :: 3
Classifier: Programming Language :: Python :: 3.7
